loaderch/__init__.py
loaderch/__main__.py
loaderch/loaderch.py
loaderch-0.1.2.dist-info/LICENSE
loaderch-0.1.2.dist-info/METADATA
loaderch-0.1.2.dist-info/WHEEL
loaderch-0.1.2.dist-info/top_level.txt
loaderch-0.1.2.dist-info/RECORD
