Metadata-Version: 2.1
Name: loaderch
Version: 0.1.2
Summary: Uploader tool for flashing firmware onto the CH552 device. v0.1.2
Author: Master
Author-email: name@email.com
License: GPL-3.0 License
License-File: LICENSE
Requires-Dist: tk
Requires-Dist: pyusb
